trampoline_client/__init__.py
trampoline_client/client.py
trampoline_client-0.1.10.dist-info/METADATA
trampoline_client-0.1.10.dist-info/WHEEL
trampoline_client-0.1.10.dist-info/RECORD
