Metadata-Version: 2.4
Name: trampoline-client
Version: 0.1.10
Summary: Python client for Trampoline dynamic reverse proxy
Keywords: proxy,tunnel,websocket,nat-traversal
Author: Bobby Lange
Author-email: contact@robertlange.me
Requires-Python: >=3.9,<4.0
Classifier: Development Status :: 3 - Alpha
Classifier: Intended Audience :: Developers
Classifier: License :: OSI Approved :: MIT License
Classifier: Programming Language :: Python :: 3
Classifier: Programming Language :: Python :: 3.9
Classifier: Programming Language :: Python :: 3.10
Classifier: Programming Language :: Python :: 3.11
Classifier: Programming Language :: Python :: 3.12
Classifier: Programming Language :: Python :: 3.13
Classifier: Programming Language :: Python :: 3.14
Requires-Dist: httpx (>=0.28.0,<1.0.0)
Requires-Dist: websockets (>=12.0,<20.0)
